autosys/.vscodeignore
autosys/CODING_STANDARDS.md
autosys/_version.py
autosys/cli/__init__.py
autosys/cli/anansi.py
autosys/cli/ansi_codes.py
autosys/cli/ascii_chars.py
autosys/cli/colors/__init__.py
autosys/cli/colors/_color_data.py
autosys/cli/colors/_css4.py
autosys/cli/colors/_matplotlib.py
autosys/cli/colors/_tableau_colors.py
autosys/cli/colors/_xkcd_colors.py
autosys/cli/terminal.py
autosys/debug/__init__.py
autosys/debug/dbprint.py
autosys/debug/debug_utils.py
autosys/debug/errc.py
autosys/debug/log.py
autosys/defaults.py
autosys/examples/__init__.py
autosys/examples/cards.py
autosys/examples/traceback_example.py
autosys/exceptions/exceptions.py
autosys/implore/contact.py
autosys/implore/implore.py
autosys/implore/sentMessage.scpt
autosys/implore/text.py
autosys/implore/webpage.py
autosys/log/__init__.py
autosys/log/fakelog.py
autosys/math_utils/__init__.py
autosys/parse/__init__.py
autosys/parse/autodoc.py
autosys/parse/example_file.py
autosys/parse/fstring_list.py
autosys/parse/lister.py
autosys/parse/markdown.py
autosys/parse/print_parens.py
autosys/parse/remove_lines.py
autosys/parse/sample_data/covid_19_data.html
autosys/parse/sample_data/covid_19_data.py
autosys/parse/str.tsts.py
autosys/parse/string_helpers.py
autosys/planner.md
autosys/profile/__init__.py
autosys/profile/autosys_time_it.py
autosys/profile/fibs.py
autosys/profile/profile_fstrings.py
autosys/text_utils/nowandthen.py
autosys/twitter/__init__.py
autosys/twitter/twitter.py
autosys/twitter/twitter_json_credentials_example.py
autosys/utils/__init__ 2.py
autosys/utils/__init__.py
autosys/utils/a_all_export.py
autosys/utils/a_get_locale.py
autosys/utils/a_memoize.py
autosys/utils/class_methods.py
autosys/utils/clipboard_watcher.py
autosys/utils/dns.py
autosys/utils/export_utils.py
autosys/utils/get_encoding.py
autosys/utils/get_search_paths.py
autosys/utils/git.py
autosys/utils/inspector.py
autosys/utils/log_urls.py
autosys/utils/ls_output.txt
autosys/utils/pathfinder.py
autosys-1.5.3.dist-info/LICENSE
autosys-1.5.3.dist-info/WHEEL
autosys-1.5.3.dist-info/METADATA
autosys-1.5.3.dist-info/RECORD
