Metadata-Version: 2.1
Name: autosys
Version: 1.5.3
Summary: System Utilities for Python on macOS.
Home-page: https://skeptycal.github.io/autosys
License: MIT
Keywords: macOS,setup,terminal,ci,tox,cli,poetry,pyproject,toml
Author: skeptycal
Author-email: skeptycal@gmail.com
Maintainer: skeptycal
Maintainer-email: skeptycal@gmail.com 
Requires-Python: >=3.8,<4.0
Classifier: License :: OSI Approved :: MIT License
Classifier: Programming Language :: Python
Classifier: Programming Language :: Python :: 3
Classifier: Programming Language :: Python :: 3.6
Classifier: Programming Language :: Python :: 3.7
Classifier: Programming Language :: Python :: 3.8
Classifier: Programming Language :: Python :: Implementation :: CPython
Classifier: Programming Language :: Python :: Implementation :: PyPy
Requires-Dist: appdirs (>=1.4.4,<2.0.0)
Requires-Dist: click (>=7.1.2,<8.0.0)
Requires-Dist: colorama (>=0.4.3,<0.5.0)
Requires-Dist: requests (>=2.24.0,<3.0.0)
Requires-Dist: toml (>=0.10.1,<0.11.0)
Project-URL: Repository, https://github.com/skeptycal/autosys
